{"application": "richpush", "exclude": [], "expectedArtifacts": [], "id": "56008c6c-f012-4aeb-b897-c6802d48d82a", "index": 5, "keepWaitingPipelines": false, "lastModifiedBy": "alexis.reuge@airship.com", "limitConcurrent": true, "name": "richpush-target-consumer-1 Rolling Deploy", "notifications": [], "parameterConfig": [], "schema": "v2", "stages": [], "template": {"artifactAccount": "front50ArtifactCredentials", "reference": "spinnaker://66d04212-082f-43da-a9e1-083e655c0e7e:latest", "type": "front50/pipelineTemplate"}, "triggers": [], "type": "templatedPipeline", "updateTs": "1663083738307", "variables": {"deployment": "richpush-target-consumer-1", "eucsProject": "ua-ops-transitional-eucs", "minReady": "0s", "prodProject": "ua-ops-transitional-prod", "stagProject": "ua-ops-transitional-stag"}}