{"application": "janine", "exclude": [], "expectedArtifacts": [], "id": "6f34788c-443c-47cf-8c90-2caa83832f52", "index": 0, "keepWaitingPipelines": false, "lastModifiedBy": "andy.quick@airship.com", "limitConcurrent": true, "name": "janine-1 Rolling Deploy", "notifications": [], "parameterConfig": [], "schema": "v2", "stages": [], "template": {"artifactAccount": "front50ArtifactCredentials", "reference": "spinnaker://66d04212-082f-43da-a9e1-083e655c0e7e:latest", "type": "front50/pipelineTemplate"}, "triggers": [], "type": "templatedPipeline", "updateTs": "1616476399021", "variables": {"deployment": "janine-1", "eucsProject": "ua-ops-transitional-eucs", "minReady": "0s", "prodProject": "ua-ops-transitional-prod", "stagProject": "ua-ops-transitional-stag"}}